DbFactory/__init__.py
DbFactory/db_factory.py
DbFactory/client/__init__.py
DbFactory/client/db_base.py
DbFactory/client/kafka_client.py
DbFactory/client/mysql_client.py
DbFactory/client/redis_client.py
DbFactory/client/redis_cluster_client.py
DbFactory/mixin/__init__.py
DbFactory/mixin/kafka_mixin.py
DbFactory/mixin/mysql_mixin.py
DbFactory/mixin/redis_mixin.py
DbFactory/mixin/sample.py
DbFactory/util/__init__.py
DbFactory/util/bytes_decoder.py
DbFactory/util/decorator.py
DbFactory/util/decorator_redis_cache.py
DbFactory/util/mini_redis.py
DbFactory/util/singleton.py
DbFactory/util/six.py
DbFactory/util/sync_redis_handler.py
DbFactory-1.0.12.dist-info/METADATA
DbFactory-1.0.12.dist-info/WHEEL
DbFactory-1.0.12.dist-info/top_level.txt
DbFactory-1.0.12.dist-info/RECORD
